confstar/__init__.py
confstar/__version__.py
confstar/loader.py
confstar/types.py
confstar/utils.py
confstar-1.0.0.dist-info/LICENSE
confstar-1.0.0.dist-info/METADATA
confstar-1.0.0.dist-info/WHEEL
confstar-1.0.0.dist-info/top_level.txt
confstar-1.0.0.dist-info/RECORD
