Metadata-Version: 2.1
Name: confstar
Version: 1.0.0
Summary: Extended Config Loader
Author-email: Ivanov Cyril <jcommander13@yandex.ru>
License: GPLv2+
Project-URL: Homepage, https://github.com/uselessvevo/confstar
Keywords: configuration,config,settings,handlers
Classifier: Operating System :: Microsoft :: Windows
Classifier: Operating System :: POSIX :: Linux
Classifier: Programming Language :: Python :: 3
Classifier: Programming Language :: Python :: 3.8
Classifier: Programming Language :: Python :: 3.9
Classifier: Programming Language :: Python :: 3.10
Classifier: Intended Audience :: Developers
Classifier: License :: OSI Approved :: GNU General Public License v2 (GPLv2)
Classifier: Natural Language :: English
License-File: LICENSE
Provides-Extra: dev
Requires-Dist: colorama ==0.4.6 ; extra == 'dev'
Requires-Dist: iniconfig ==2.0.0 ; extra == 'dev'
Requires-Dist: packaging ==23.2 ; extra == 'dev'
Requires-Dist: pluggy ==1.3.0 ; extra == 'dev'
Requires-Dist: pytest ==7.4.3 ; extra == 'dev'
